{
    "type": "Feature",
    "stac_version": "1.0.0",
    "stac_extensions": [
        "https://stac-extensions.github.io/view/v1.0.0/schema.json",
        "https://stac-extensions.github.io/projection/v1.0.0/schema.json",
        "https://stac-extensions.github.io/eo/v1.0.0/schema.json",
        "https://stac-extensions.github.io/raster/v1.1.0/schema.json",
        "https://stac-extensions.github.io/grid/v1.0.0/schema.json"
    ],
    "id": "4/122000330133/105001003590C300",
    "properties": {
        "datetime": "2023-08-12 21:18:19Z",
        "platform": "GE01",
        "gsd": 0.5,
        "ard_metadata_version": "0.0.1",
        "catalog_id": "105001003590C300",
        "utm_zone": 4,
        "quadkey": "122000330133",
        "view:off_nadir": 26.3,
        "view:azimuth": 299.8,
        "view:incidence_angle": 60.6,
        "view:sun_azimuth": 105.8,
        "view:sun_elevation": 71.9,
        "proj:epsg": 32604,
        "proj:geometry": {
            "type": "Polygon",
            "coordinates": [
                [
                    [
                        774843.75,
                        2305156.25
                    ],
                    [
                        774843.75,
                        2299843.75
                    ],
                    [
                        780156.25,
                        2299843.75
                    ],
                    [
                        780156.25,
                        2305156.25
                    ],
                    [
                        774843.75,
                        2305156.25
                    ]
                ]
            ]
        },
        "grid:code": "MXRA-Z4-122000330133",
        "proj:bbox": [
            774843.75,
            2299843.75,
            780156.25,
            2305156.25
        ],
        "tile:data_area": 28.2,
        "tile:clouds_area": 1.2,
        "tile:clouds_percent": 4
    },
    "bbox": [
        -156.36004748800423,
        20.77736903827452,
        -156.30821017009256,
        20.826112721532844
    ],
    "geometry": {
        "type": "Polygon",
        "coordinates": [
            [
                [
                    -156.3592122961001,
                    20.826112721532844
                ],
                [
                    -156.36004748800423,
                    20.778160951844843
                ],
                [
                    -156.30906144522334,
                    20.77736903827452
                ],
                [
                    -156.30821017009256,
                    20.82531881502999
                ],
                [
                    -156.3592122961001,
                    20.826112721532844
                ]
            ]
        ]
    },
    "links": [
        {
            "rel": "collection",
            "href": "../../../acquisition_collections/105001003590C300_collection.json",
            "type": "application/json"
        },
        {
            "rel": "parent",
            "href": "../../../acquisition_collections/105001003590C300_collection.json",
            "type": "application/json"
        },
        {
            "rel": "root",
            "href": "../../../order_collections/6252269831086136329_root_collection.json",
            "type": "application/json"
        }
    ],
    "assets": {
        "data-mask": {
            "type": "application/geopackage+sqlite3",
            "title": "Data Mask",
            "href": "./105001003590C300-data-mask.gpkg",
            "roles": [
                "data-mask"
            ]
        },
        "ms_analytic": {
            "type": "image/tiff; application=geotiff; profile=cloud-optimized",
            "title": "Multispectral Image",
            "href": "https://maxar-opendata.s3.amazonaws.com/events/Maui-Hawaii-fires-Aug-23/ard/04/122000330133/2023-08-12/105001003590C300-ms.tif",
            "proj:bbox": [
                774843.75,
                2299843.75,
                780156.25,
                2305156.25
            ],
            "proj:shape": [
                2784,
                2784
            ],
            "proj:transform": [
                1.9082255747126438,
                0.0,
                774843.75,
                0.0,
                -1.9082255747126438,
                2305156.25,
                0.0,
                0.0,
                1.0
            ],
            "eo:bands": [
                {
                    "name": "BAND_B",
                    "common_name": "blue",
                    "description": "Blue"
                },
                {
                    "name": "BAND_G",
                    "common_name": "green",
                    "description": "Green"
                },
                {
                    "name": "BAND_R",
                    "common_name": "red",
                    "description": "Red"
                },
                {
                    "name": "BAND_N",
                    "common_name": "nir08",
                    "description": "Near Infrared 1"
                }
            ],
            "roles": [
                "data"
            ],
            "raster:bands": [
                {
                    "data_type": "uint16"
                }
            ]
        },
        "pan_analytic": {
            "type": "image/tiff; application=geotiff; profile=cloud-optimized",
            "title": "Panchromatic Image",
            "href": "https://maxar-opendata.s3.amazonaws.com/events/Maui-Hawaii-fires-Aug-23/ard/04/122000330133/2023-08-12/105001003590C300-pan.tif",
            "proj:bbox": [
                774843.75,
                2299843.75,
                780156.25,
                2305156.25
            ],
            "proj:shape": [
                11136,
                11136
            ],
            "proj:transform": [
                0.47705639367816094,
                0.0,
                774843.75,
                0.0,
                -0.47705639367816094,
                2305156.25,
                0.0,
                0.0,
                1.0
            ],
            "eo:bands": [
                {
                    "name": "BAND_P",
                    "description": "Pan"
                }
            ],
            "roles": [
                "data"
            ],
            "raster:bands": [
                {
                    "data_type": "uint16"
                }
            ]
        },
        "visual": {
            "type": "image/tiff; application=geotiff; profile=cloud-optimized",
            "title": "Visual Image",
            "href": "https://maxar-opendata.s3.amazonaws.com/events/Maui-Hawaii-fires-Aug-23/ard/04/122000330133/2023-08-12/105001003590C300-visual.tif",
            "proj:bbox": [
                774843.75,
                2299843.75,
                780156.25,
                2305156.25
            ],
            "proj:shape": [
                17408,
                17408
            ],
            "proj:transform": [
                0.30517578125,
                0.0,
                774843.75,
                0.0,
                -0.30517578125,
                2305156.25,
                0.0,
                0.0,
                1.0
            ],
            "eo:bands": [
                {
                    "name": "BAND_R",
                    "common_name": "red",
                    "description": "Red"
                },
                {
                    "name": "BAND_G",
                    "common_name": "green",
                    "description": "Green"
                },
                {
                    "name": "BAND_B",
                    "common_name": "blue",
                    "description": "Blue"
                }
            ],
            "roles": [
                "visual"
            ],
            "raster:bands": [
                {
                    "data_type": "uint16"
                }
            ]
        }
    },
    "collection": "105001003590C300"
}